gradnet/__init__.py
gradnet/gradnet.py
gradnet/ode.py
gradnet/trainer.py
gradnet/utils.py
gradnet-0.1.10.dist-info/METADATA
gradnet-0.1.10.dist-info/WHEEL
gradnet-0.1.10.dist-info/licenses/LICENSE
gradnet-0.1.10.dist-info/RECORD
