Metadata-Version: 2.4
Name: gradnet
Version: 0.1.10
Summary: Trainable graph adjacency parameterizations with ODE integration and Lightning training helpers.
Project-URL: Homepage, https://mikaberidze.github.io/
Project-URL: Documentation, https://gradnet.readthedocs.io/
Project-URL: Repository, https://github.com/mikaberidze/gradnet
Author: Guram Mikaberidze, Beso Mikaberidze, Dane Taylor
License-Expression: BSD-3-Clause
License-File: LICENSE
Keywords: dynamical systems,graphs,lightning,networks,ode,optimization,pytorch
Classifier: Development Status :: 3 - Alpha
Classifier: Intended Audience :: Science/Research
Classifier: License :: OSI Approved :: BSD License
Classifier: Operating System :: OS Independent
Classifier: Programming Language :: Python :: 3
Classifier: Programming Language :: Python :: 3.10
Classifier: Topic :: Scientific/Engineering :: Artificial Intelligence
Classifier: Topic :: Scientific/Engineering :: Mathematics
Requires-Python: >=3.10
Requires-Dist: numpy>=1.21
Requires-Dist: pytorch-lightning<3,>=1.9
Requires-Dist: torch>=2.0
Requires-Dist: torchdiffeq>=0.2.3
Requires-Dist: tqdm>=4.64
Provides-Extra: networkx
Requires-Dist: networkx>=2.6; extra == 'networkx'
